MANIFEST.in
README.md
environment.yml
pyproject.toml
requirements-package.txt
requirements.txt
setup.cfg
setup.py
illusionist/__init__.py
illusionist/_generated_version.py
illusionist/client.py
illusionist/exporter_html.py
illusionist/exporter_nb.py
illusionist/kernel_utils.py
illusionist/preprocessor.py
illusionist/utils.py
illusionist/widgets.py
illusionist.egg-info/PKG-INFO
illusionist.egg-info/SOURCES.txt
illusionist.egg-info/dependency_links.txt
illusionist.egg-info/entry_points.txt
illusionist.egg-info/not-zip-safe
illusionist.egg-info/requires.txt
illusionist.egg-info/top_level.txt
illusionist/tests/__init__.py
illusionist/tests/test_hash_fn.py
illusionist/tests/test_import.py
illusionist/tests/test_possible_values.py
illusionist/tests/test_preprocessor.py
illusionist/tests/test_widget_matrix.py
illusionist/tests/utils.py
share/jupyter/nbconvert/templates/.DS_Store
share/jupyter/nbconvert/templates/illusionist/conf.json
share/jupyter/nbconvert/templates/illusionist/index.html.j2
share/jupyter/nbconvert/templates/illusionist/static/dist/.gitignore
share/jupyter/nbconvert/templates/illusionist/static/dist/1.illusionist-embed.js
share/jupyter/nbconvert/templates/illusionist/static/dist/1.illusionist-embed.js.map
share/jupyter/nbconvert/templates/illusionist/static/dist/1.illusionist.js
share/jupyter/nbconvert/templates/illusionist/static/dist/1.illusionist.js.map
share/jupyter/nbconvert/templates/illusionist/static/dist/1e59d2330b4c6deb84b340635ed36249.ttf
share/jupyter/nbconvert/templates/illusionist/static/dist/2.illusionist-embed.js
share/jupyter/nbconvert/templates/illusionist/static/dist/2.illusionist-embed.js.map
share/jupyter/nbconvert/templates/illusionist/static/dist/2.illusionist.js
share/jupyter/nbconvert/templates/illusionist/static/dist/2.illusionist.js.map
share/jupyter/nbconvert/templates/illusionist/static/dist/20fd1704ea223900efa9fd4e869efb08.woff2
share/jupyter/nbconvert/templates/illusionist/static/dist/8b43027f47b20503057dfbbaa9401fef.eot
share/jupyter/nbconvert/templates/illusionist/static/dist/c1e38fd9e0e74ba58f7a2b77ef29fdd3.svg
share/jupyter/nbconvert/templates/illusionist/static/dist/f691f37e57f04c152e2315ab7dbad881.woff
