Metadata-Version: 2.1
Name: illusionist
Version: 0.2.0
Summary: UNKNOWN
Home-page: https://github.com/danielfrg/illusionist
Maintainer: Daniel Rodriguez
Maintainer-email: daniel@danielfrg.com
License: Apache License, Version 2.0
Platform: UNKNOWN
Classifier: License :: OSI Approved :: Apache Software License
Classifier: Programming Language :: Python :: 3.7
Classifier: Programming Language :: Python :: 3.8
Requires-Python: >=3.7
Provides-Extra: test
Provides-Extra: dev
